BlueWhale3_Recommendation-0.1.3-py3.6-nspkg.pth
orangecontrib/recommendation/__init__.py
orangecontrib/recommendation/base_recommendation.py
orangecontrib/recommendation/i18n_config.py
orangecontrib/recommendation/baseline/__init__.py
orangecontrib/recommendation/baseline/global_avg.py
orangecontrib/recommendation/baseline/item_avg.py
orangecontrib/recommendation/baseline/user_avg.py
orangecontrib/recommendation/baseline/user_item_baseline.py
orangecontrib/recommendation/datasets/binary_data.tab
orangecontrib/recommendation/datasets/binary_data_dis.tab
orangecontrib/recommendation/datasets/epinions_test.tab
orangecontrib/recommendation/datasets/epinions_train.tab
orangecontrib/recommendation/datasets/movielens100k.tab
orangecontrib/recommendation/datasets/ratings.tab
orangecontrib/recommendation/datasets/ratings_dis.tab
orangecontrib/recommendation/datasets/ratings_dis_swap.tab
orangecontrib/recommendation/datasets/filmtrust/ratings.tab
orangecontrib/recommendation/datasets/filmtrust/ratings_small.tab
orangecontrib/recommendation/datasets/filmtrust/trust.tab
orangecontrib/recommendation/datasets/filmtrust/trust_small.tab
orangecontrib/recommendation/evaluation/__init__.py
orangecontrib/recommendation/evaluation/ranking.py
orangecontrib/recommendation/locale/recommendation.en.yml
orangecontrib/recommendation/locale/recommendation.zh.yml
orangecontrib/recommendation/optimizers/__init__.py
orangecontrib/recommendation/optimizers/sgd_optimizers.py
orangecontrib/recommendation/ranking/__init__.py
orangecontrib/recommendation/ranking/base_ranking.py
orangecontrib/recommendation/ranking/climf.py
orangecontrib/recommendation/rating/__init__.py
orangecontrib/recommendation/rating/base_rating.py
orangecontrib/recommendation/rating/brismf.py
orangecontrib/recommendation/rating/svdplusplus.py
orangecontrib/recommendation/rating/trustsvd.py
orangecontrib/recommendation/tests/__init__.py
orangecontrib/recommendation/tests/coverage/__init__.py
BlueWhale3_Recommendation-0.1.3.dist-info/LICENSE.txt
BlueWhale3_Recommendation-0.1.3.dist-info/METADATA
BlueWhale3_Recommendation-0.1.3.dist-info/WHEEL
BlueWhale3_Recommendation-0.1.3.dist-info/entry_points.txt
BlueWhale3_Recommendation-0.1.3.dist-info/namespace_packages.txt
BlueWhale3_Recommendation-0.1.3.dist-info/top_level.txt
BlueWhale3_Recommendation-0.1.3.dist-info/RECORD
